{
    "type": "block",
    "pools": [
        {
            "rolls": 1,
            "entries": [
                {
                    "type": "loot_table",
                    "name": "asset:item/loot/1032.wheat_seeds/_"
                }
            ]
        },
        {
            "rolls": 1,
            "entries": [
                {
                    "type": "loot_table",
                    "name": "asset:item/loot/1031.wheat/_"
                }
            ],
            "functions": [
                {
                    "function": "set_count",
                    "count": {
                        "min": 1,
                        "max": 2
                    }
                }
            ],
            "conditions": [
                {
                    "block": "wheat",
                    "condition": "block_state_property",
                    "properties": {
                        "age": "7"
                    }
                }
            ]
        },
        {
            "rolls": 1,
            "entries": [
                {
                    "type": "loot_table",
                    "name": "asset:item/loot/1032.wheat_seeds/_"
                }
            ],
            "functions": [
                {
                    "function": "set_count",
                    "count": {
                        "min": 1,
                        "max": 2
                    }
                }
            ],
            "conditions": [
                {
                    "block": "wheat",
                    "condition": "block_state_property",
                    "properties": {
                        "age": "7"
                    }
                }
            ]
        }
    ]
}