{"pools": [{"rolls": 1,"entries": [{"type": "item","name": "nautilus_shell","functions": [{"function": "set_name","target": "item_name","name": {"text": "上質な革","color": "white"}},{"function": "set_components","components": {"item_model": "leather","max_stack_size": 64,"unbreakable": {},"enchantment_glint_override": false}},{"function": "set_custom_data","tag": "{item_id:1039,rarity:1,max_stack_size:64,lore_length:2,base_item_name:\"上質な革\",item_group_name:\"ﾄﾞﾛｯﾌﾟ\",price:34,value:5,can_sell:1b,}"},{"function": "set_lore","mode": "append","lore": [[{"text": "","color": "#D8D8D8","italic": false},{"text": "なんらかの動物の上質な革。"}],[{"text": "","color": "#D8D8D8","italic": false},{"text": "丈夫な上、風合いが柔らか。"}]]},{"function": "set_lore","mode": "append","lore": [[{"text": "","color": "dark_gray","italic": false,"strikethrough": true},{"text": "         "},{"text": "\uF822合成時\uF822","color": "#777777","strikethrough": false},{"text": "         "}]]},{"#": "アイテム種lootのcustom_data","function": "set_custom_data","tag": "{ui:{combinable:1b,brewable:1b,color:{r:243,g:153,b:32}}}"},{"#": "アイテムのステータス補正データ","function": "set_custom_data","tag": "{bonus:[{status:\"HP\",value:8},{status:\"LUK\",value:10}],base_bonus:[{status:\"HP\",value:8},{status:\"LUK\",value:10}],combine_bonus:[]}"},{"function": "set_lore","mode": "append","lore": [[{"text": "\uF823\uE100\uF823","color": "white","italic": false},{"text": "最大ＨＰ: ","color": "#E0E0E0"},{"text": "+8","color": "#72FF5C"}]]},{"function": "set_lore","mode": "append","lore": [[{"text": "\uF823\uE10B\uF823","color": "white","italic": false},{"text": "幸運: ","color": "#E0E0E0"},{"text": "+10","color": "#72FF5C"}]]},{"function": "toggle_tooltips", "toggles": {"trim":false, "dyed_color": false,"enchantments": false,"stored_enchantments":false,"unbreakable":false ,"can_break": false,"can_place_on": false,"attribute_modifiers":false}},{"function": "set_components", "components": {"hide_additional_tooltip": {}}},{"#": "アイテムのバフデータ","function": "set_custom_data","tag": "{consumables:{buff:[{status:\"HP\",amplifier:8,duration:260},{status:\"LUK\",amplifier:10,duration:380}]}}"},{"function": "set_lore","mode": "append","lore": [{"text": "                          ","color": "dark_gray","strikethrough": true}]},{"function": "set_lore","mode": "append","lore": [[{"text": "","color": "white","italic": false},{"text": "▸ﾄﾞﾛｯﾌﾟ"},{"text": "【\uE150】"}]]}]}]}]}