{"pools": [{"rolls": 1,"entries": [{"type": "item","name": "bow","functions": [{"function": "set_name","target": "item_name","name": {"text": "骨の弓","color": "#6FE58D"}},{"function": "set_components","components": {"custom_model_data": 2602,"max_stack_size": 1,"unbreakable": {},"enchantment_glint_override": false}},{"function": "set_custom_data","tag": "{rarity:2,max_stack_size:1,lore_length:1,base_item_name:\"骨の弓\",item_group_name:\"弓\",price:360,value:72,can_sell:1b,}"},{"function": "set_lore","mode": "append","lore": [[{"text": "","color": "#D8D8D8","italic": false},{"text": "しなる骨から作られた弓。"}]]},{"function": "set_lore","mode": "append","lore": [[{"text": "","color": "dark_gray","italic": false,"strikethrough": true},{"text": "         "},{"text": "\uF822装備時\uF822","color": "#777777","strikethrough": false},{"text": "         "}]]},{"#": "アイテム種weaponのcustom_data","function": "set_custom_data","tag": "{weapon:\"bow\",offhand:1b,grade:0}"},{"function": "set_attributes","modifiers": [{"attribute": "attack_speed","id": "attack_speed","amount": -1.0,"operation": "add_value","slot": "mainhand"}]},{"function": "set_enchantments","enchantments": {"player:bow": 1}},{"#": "カスタムエンチャント","function": "set_custom_data","tag": "{ui:{enchantable:1b}}"},{"#": "アイテムのステータス補正データ","function": "set_custom_data","tag": "{bonus:[{status:\"DEX\",value:18},{status:\"AGI\",value:43}],base_bonus:[{status:\"DEX\",value:18},{status:\"AGI\",value:43}],combine_bonus:[]}"},{"function": "set_lore","mode": "append","lore": [[{"text": "\uF823\uE106\uF823","color": "white","italic": false},{"text": "器用さ: ","color": "#E0E0E0"},{"text": "+18","color": "#72FF5C"}]]},{"function": "set_lore","mode": "append","lore": [[{"text": "\uF823\uE109\uF823","color": "white","italic": false},{"text": "素早さ: ","color": "#E0E0E0"},{"text": "+43","color": "#72FF5C"}]]},{"#": "強化素材","function": "set_custom_data","tag": "{ui:{smithable:1b,upgrade:[[{count:4,Slot:12b,id:\"bone_meal\",components:{\"custom_model_data\":1037,\"custom_data\":{ui:{item_type:\"blank\"}},\"item_name\":'{\"color\":\"white\",\"text\":\"骨粉\"}',\"lore\":['[{\"text\":\"\",\"color\":\"gray\",\"italic\":false},{\"text\":\"崩れて粉々になった骨。\"}]','[{\"text\":\"\",\"color\":\"gray\",\"italic\":false},{\"text\":\"よく肥料として用いられる。\"}]']}},{count:6,Slot:13b,id:\"nautilus_shell\",components:{\"custom_model_data\":1021,\"custom_data\":{ui:{item_type:\"blank\"}},\"item_name\":'{\"color\":\"white\",\"text\":\"脆いホネ\"}',\"lore\":['[{\"text\":\"\",\"color\":\"gray\",\"italic\":false},{\"text\":\"色の濁った崩れかけのホネ。\"}]','[{\"text\":\"\",\"color\":\"gray\",\"italic\":false},{\"text\":\"奇跡的にも形を保っている。\"}]']}},{count:3,Slot:14b,id:\"nautilus_shell\",components:{\"custom_model_data\":1040,\"custom_data\":{ui:{item_type:\"blank\"}},\"item_name\":'{\"color\":\"white\",\"text\":\"滑らかな糸\"}',\"lore\":['[{\"text\":\"\",\"color\":\"gray\",\"italic\":false},{\"text\":\"すべすべでさらさらな糸。\"}]','[{\"text\":\"\",\"color\":\"gray\",\"italic\":false},{\"text\":\"しなやかでとっても頑丈。\"}]']}}],[{count:6,Slot:12b,id:\"bone_meal\",components:{\"custom_model_data\":1037,\"custom_data\":{ui:{item_type:\"blank\"}},\"item_name\":'{\"color\":\"white\",\"text\":\"骨粉\"}',\"lore\":['[{\"text\":\"\",\"color\":\"gray\",\"italic\":false},{\"text\":\"崩れて粉々になった骨。\"}]','[{\"text\":\"\",\"color\":\"gray\",\"italic\":false},{\"text\":\"よく肥料として用いられる。\"}]']}},{count:9,Slot:13b,id:\"nautilus_shell\",components:{\"custom_model_data\":1021,\"custom_data\":{ui:{item_type:\"blank\"}},\"item_name\":'{\"color\":\"white\",\"text\":\"脆いホネ\"}',\"lore\":['[{\"text\":\"\",\"color\":\"gray\",\"italic\":false},{\"text\":\"色の濁った崩れかけのホネ。\"}]','[{\"text\":\"\",\"color\":\"gray\",\"italic\":false},{\"text\":\"奇跡的にも形を保っている。\"}]']}},{count:4,Slot:14b,id:\"nautilus_shell\",components:{\"custom_model_data\":1036,\"custom_data\":{ui:{item_type:\"blank\"}},\"item_name\":'{\"color\":\"white\",\"text\":\"スライムボール\"}',\"lore\":['[{\"text\":\"\",\"color\":\"gray\",\"italic\":false},{\"text\":\"色の濁った崩れかけのホネ。\"}]','[{\"text\":\"\",\"color\":\"gray\",\"italic\":false},{\"text\":\"奇跡的にも形を保っている。\"}]']}}],[{count:9,Slot:12b,id:\"bone_meal\",components:{\"custom_model_data\":1037,\"custom_data\":{ui:{item_type:\"blank\"}},\"item_name\":'{\"color\":\"white\",\"text\":\"骨粉\"}',\"lore\":['[{\"text\":\"\",\"color\":\"gray\",\"italic\":false},{\"text\":\"崩れて粉々になった骨。\"}]','[{\"text\":\"\",\"color\":\"gray\",\"italic\":false},{\"text\":\"よく肥料として用いられる。\"}]']}},{count:13,Slot:13b,id:\"nautilus_shell\",components:{\"custom_model_data\":1021,\"custom_data\":{ui:{item_type:\"blank\"}},\"item_name\":'{\"color\":\"white\",\"text\":\"脆いホネ\"}',\"lore\":['[{\"text\":\"\",\"color\":\"gray\",\"italic\":false},{\"text\":\"色の濁った崩れかけのホネ。\"}]','[{\"text\":\"\",\"color\":\"gray\",\"italic\":false},{\"text\":\"奇跡的にも形を保っている。\"}]']}},{count:2,Slot:14b,id:\"nautilus_shell\",components:{\"custom_model_data\":1022,\"custom_data\":{ui:{item_type:\"blank\"}},\"item_name\":'{\"color\":\"#7C7CE8\",\"text\":\"黄金のホネ\"}',\"lore\":['[{\"text\":\"\",\"color\":\"gray\",\"italic\":false},{\"text\":\"神秘的に黄金色に輝くホネ。\"}]','[{\"text\":\"\",\"color\":\"gray\",\"italic\":false},{\"text\":\"どうしてか金属的な光沢が。\"}]']}}]]}}"},{"#": "合成スロット","function": "set_custom_data","tag": "{ui:{smithable:1b,combine:[{count:1b,Slot:13b,id:\"glass_bottle\",components:{\"custom_model_data\":3004,\"custom_data\":{ui:{item_type:\"blank\"}},\"item_name\":'\"【\uE152】以上で解放\"'}},{count:1b,Slot:14b,id:\"glass_bottle\",components:{\"custom_model_data\":3004,\"custom_data\":{ui:{item_type:\"blank\"}},\"item_name\":'\"【\uE153】以上で解放\"'}},]}}"},{"function": "toggle_tooltips", "toggles": {"trim":false, "dyed_color": false,"enchantments": false,"stored_enchantments":false,"unbreakable":false ,"can_break": false,"can_place_on": false,"attribute_modifiers":false}},{"function": "set_components", "components": {"hide_additional_tooltip": {}}},{"function": "set_lore","mode": "append","lore": [{"text": "                          ","color": "dark_gray","strikethrough": true}]},{"function": "set_lore","mode": "append","lore": [[{"text": "","color": "white","italic": false},{"text": "▸弓"},{"text": "【\uE151】"}]]}]}]}]}